telemetrix_pca9685/__init__.py
telemetrix_pca9685/pca9685_constants.py
telemetrix_pca9685/telemetrix_pca9685.py
telemetrix_pca9685/telemetrix_pca9685_aio.py
telemetrix_extensions-1.0.dist-info/METADATA
telemetrix_extensions-1.0.dist-info/WHEEL
telemetrix_extensions-1.0.dist-info/top_level.txt
telemetrix_extensions-1.0.dist-info/RECORD
