Metadata-Version: 2.1
Name: telemetrix-extensions
Version: 1.0
Summary: i2c Extensions For Telemetrix Clients
Home-page: https://github.com/MrYsLab/telemetrix-extensions
Author: Alan Yorinks
Author-email: MisterYsLab@gmail.com
License: UNKNOWN
Download-URL: https://github.com/MrYsLab/telemetrix-extensions
Keywords: telemetrix,Arduino,Raspberry Pi Pico,Protocol,Python
Platform: UNKNOWN
Classifier: Development Status :: 5 - Production/Stable
Classifier: Environment :: Other Environment
Classifier: Intended Audience :: Developers
Classifier: Intended Audience :: Education
Classifier: License :: OSI Approved :: GNU Affero General Public License v3 or later (AGPLv3+)
Classifier: Operating System :: OS Independent
Classifier: Programming Language :: Python :: 3.7
Classifier: Programming Language :: Python :: 3.8
Classifier: Topic :: Software Development :: Libraries :: Python Modules
Requires-Dist: telemetrix
Requires-Dist: telemetrix-aio
Requires-Dist: telemetrix-rpi-pico
Requires-Dist: tmx-pico-aio
